jupyterexcel/__init__.py
jupyterexcel/server_extension.py
jupyterexcel/utils.py
jupyterexcel-0.0.11.dist-info/LICENSE
jupyterexcel-0.0.11.dist-info/METADATA
jupyterexcel-0.0.11.dist-info/WHEEL
jupyterexcel-0.0.11.dist-info/top_level.txt
jupyterexcel-0.0.11.dist-info/RECORD
