Metadata-Version: 2.1
Name: jupyterexcel
Version: 0.0.11
Summary: A python Jupyter extensions to make notebooks web api for Excel to call using UDF forumla or Ribbon Callback. Jupyter Excel, Python Excel
Home-page: https://github.com/luozhijian/jupyterexcel
Author: Jim Luo
Author-email: luozhijian@gmail.com
License: UNKNOWN
Platform: UNKNOWN
Classifier: Programming Language :: Python :: 3
Classifier: License :: OSI Approved :: MIT License
Classifier: Operating System :: OS Independent
